scripts/__init__.py
scripts/create-release-tag.sh
scripts/create_release.py
scripts/run_
scripts/setup-poetry-env.ps1
scripts/upload-to-pypi.sh
sprigconfig/__init__.md
sprigconfig/__init__.py
sprigconfig/cli.md
sprigconfig/cli.py
sprigconfig/config.md
sprigconfig/config.py
sprigconfig/config_loader.md
sprigconfig/config_loader.py
sprigconfig/config_singleton.md
sprigconfig/config_singleton.py
sprigconfig/deepmerge.md
sprigconfig/deepmerge.py
sprigconfig/exceptions.md
sprigconfig/exceptions.py
sprigconfig/help.md
sprigconfig/help.py
sprigconfig/injection.md
sprigconfig/injection.py
sprigconfig/instantiate.md
sprigconfig/instantiate.py
sprigconfig/lazy_secret.md
sprigconfig/lazy_secret.py
sprigconfig/parsers/__init__.md
sprigconfig/parsers/__init__.py
sprigconfig/parsers/json_parser.md
sprigconfig/parsers/json_parser.py
sprigconfig/parsers/toml_parser.md
sprigconfig/parsers/toml_parser.py
sprigconfig/parsers/yaml_parser.md
sprigconfig/parsers/yaml_parser.py
sprig_config-1.4.3.dist-info/METADATA
sprig_config-1.4.3.dist-info/WHEEL
sprig_config-1.4.3.dist-info/entry_points.txt
sprig_config-1.4.3.dist-info/licenses/LICENSE
sprig_config-1.4.3.dist-info/RECORD
