Metadata-Version: 2.4
Name: sprig-config
Version: 1.4.3
Summary: Spring-like deep merge configuration loader for Python
License: MIT
License-File: LICENSE
Author: Derik G. Wilson
Author-email: derikwilson6@gmail.com
Requires-Python: >=3.13,<4.0
Classifier: License :: OSI Approved :: MIT License
Classifier: Programming Language :: Python :: 3
Classifier: Programming Language :: Python :: 3.13
Classifier: Programming Language :: Python :: 3.14
Requires-Dist: PyYAML (>=6.0.2)
Requires-Dist: cryptography (>=46.0.1,<47.0.0)
Project-URL: Changelog, https://github.com/derikgw/sprig-config/blob/main/CHANGELOG.md
Project-URL: Documentation, https://derikgw.github.io/sprig-config/
Project-URL: Homepage, https://derikgw.github.io/sprig-config/
Project-URL: Issues, https://github.com/derikgw/sprig-config/issues
Project-URL: Repository, https://github.com/derikgw/sprig-config
